balokBeton/ACI318.py
balokBeton/Balok.py
balokBeton/Reinforcement.py
balokBeton/SNI2847.py
balokBeton/Sketch.py
balokBeton/__init__.py
balokBeton-0.1.dist-info/METADATA
balokBeton-0.1.dist-info/WHEEL
balokBeton-0.1.dist-info/top_level.txt
balokBeton-0.1.dist-info/RECORD
